logic_bank_utils/util.py
logicbankutils-0.6.0.dist-info/LICENSE
logicbankutils-0.6.0.dist-info/METADATA
logicbankutils-0.6.0.dist-info/WHEEL
logicbankutils-0.6.0.dist-info/top_level.txt
logicbankutils-0.6.0.dist-info/RECORD
