Metadata-Version: 2.1
Name: logicbankutils
Version: 0.6.0
Summary: Utility functions for LogicBase
Home-page: https://github.com/valhuber/logicbankutils
Author: Val Huber
Author-email: valjhuber@gmail.com
License: BSD
Project-URL: Docs, https://github.com/valhuber/logicbankutils/wiki
Platform: any
Classifier: Development Status :: 3 - Alpha
Classifier: Environment :: Web Environment
Classifier: Intended Audience :: Developers
Classifier: License :: OSI Approved :: BSD License
Classifier: Operating System :: OS Independent
Classifier: Programming Language :: Python
Classifier: Topic :: Software Development :: Libraries :: Python Modules
Requires-Python: ~=3.8
